[
  {
    "id": "importadora-asia-sp",
    "slug": "importadora-asia-sp",
    "name": "Importadora Asia SP",
    "marketplaces": ["ML", "Shopee"],
    "skus_in_conflict": 6,
    "last_price_change": "há 40min",
    "tracked_since": "04/04/2026",
    "reputation": 4.7,
    "avg_price_diff": -0.35,
    "aggressiveness": "Alta",
    "price_changes_per_week": 12,
    "common_change_hours": "08h–10h e 20h–22h",
    "sku_conflicts": [
      { "sku": "Molho Especial Tarê Sakura 1L", "our_price": 24.99, "their_price": 24.89, "diff": -0.10, "last_action": "Baixou R$0,10 há 40min" },
      { "sku": "Shoyu Daimaru Macro Especial 900ml", "our_price": 25.90, "their_price": 22.90, "diff": -3.00, "last_action": "Baixou R$1,50 há 3 dias" },
      { "sku": "Shoyu Tradicional 1L Sakura", "our_price": 18.90, "their_price": 18.40, "diff": -0.50, "last_action": "Entrou no mercado 04/04" },
      { "sku": "Bifum 500g Chi-Mifen", "our_price": 15.90, "their_price": 16.30, "diff": 0.40, "last_action": "Sem mudança 7 dias" },
      { "sku": "Alga Nori 10fls Hanaro", "our_price": 12.90, "their_price": 13.10, "diff": 0.20, "last_action": "Subiu R$0,20 há 2 dias" },
      { "sku": "Alga Nori 10fls Sakura", "our_price": 12.50, "their_price": 12.70, "diff": 0.20, "last_action": "Sem mudança 5 dias" }
    ],
    "recent_actions": [
      { "date": "13/04 09h15", "action": "Baixou Tarê Sakura de R$25,09 para R$24,89" },
      { "date": "12/04 20h42", "action": "Baixou Shoyu Daimaru de R$23,40 para R$22,90" },
      { "date": "10/04 08h03", "action": "Entrou com Shoyu Tradicional a R$18,40" },
      { "date": "09/04 21h18", "action": "Baixou Shoyu Daimaru de R$24,90 para R$23,40" },
      { "date": "07/04 09h55", "action": "Subiu Alga Nori Hanaro de R$12,90 para R$13,10" }
    ]
  },
  {
    "id": "oriental-market-br",
    "slug": "oriental-market-br",
    "name": "Oriental Market BR",
    "marketplaces": ["ML", "Amazon"],
    "skus_in_conflict": 4,
    "last_price_change": "há 2h",
    "tracked_since": "15/03/2026",
    "reputation": 4.5,
    "avg_price_diff": -0.22,
    "aggressiveness": "Média",
    "price_changes_per_week": 5
  },
  {
    "id": "casa-do-shoyu",
    "slug": "casa-do-shoyu",
    "name": "Casa do Shoyu",
    "marketplaces": ["Shopee"],
    "skus_in_conflict": 3,
    "last_price_change": "há 1 dia",
    "tracked_since": "20/02/2026",
    "reputation": 4.2,
    "avg_price_diff": -1.40,
    "aggressiveness": "Alta",
    "price_changes_per_week": 9
  },
  {
    "id": "distribuidora-nikkei",
    "slug": "distribuidora-nikkei",
    "name": "Distribuidora Nikkei",
    "marketplaces": ["ML", "Shopee", "Amazon"],
    "skus_in_conflict": 7,
    "last_price_change": "há 3h",
    "tracked_since": "01/03/2026",
    "reputation": 4.8,
    "avg_price_diff": 0.15,
    "aggressiveness": "Baixa",
    "price_changes_per_week": 2
  },
  {
    "id": "emporio-yamamoto",
    "slug": "emporio-yamamoto",
    "name": "Empório Yamamoto",
    "marketplaces": ["ML"],
    "skus_in_conflict": 5,
    "last_price_change": "há 6h",
    "tracked_since": "10/03/2026",
    "reputation": 4.6,
    "avg_price_diff": -0.55,
    "aggressiveness": "Média",
    "price_changes_per_week": 6
  },
  {
    "id": "sabores-do-oriente",
    "slug": "sabores-do-oriente",
    "name": "Sabores do Oriente",
    "marketplaces": ["Shopee", "Amazon"],
    "skus_in_conflict": 2,
    "last_price_change": "há 5h",
    "tracked_since": "28/02/2026",
    "reputation": 4.1,
    "avg_price_diff": -0.80,
    "aggressiveness": "Alta",
    "price_changes_per_week": 11
  },
  {
    "id": "tokyo-imports-br",
    "slug": "tokyo-imports-br",
    "name": "Tokyo Imports BR",
    "marketplaces": ["ML"],
    "skus_in_conflict": 3,
    "last_price_change": "há 1 dia",
    "tracked_since": "05/03/2026",
    "reputation": 4.4,
    "avg_price_diff": -0.30,
    "aggressiveness": "Média",
    "price_changes_per_week": 4
  },
  {
    "id": "asia-gourmet-sp",
    "slug": "asia-gourmet-sp",
    "name": "Asia Gourmet SP",
    "marketplaces": ["ML", "Amazon"],
    "skus_in_conflict": 4,
    "last_price_change": "há 8h",
    "tracked_since": "18/03/2026",
    "reputation": 4.9,
    "avg_price_diff": 0.25,
    "aggressiveness": "Baixa",
    "price_changes_per_week": 1
  },
  {
    "id": "mercado-oriental-rj",
    "slug": "mercado-oriental-rj",
    "name": "Mercado Oriental RJ",
    "marketplaces": ["Shopee"],
    "skus_in_conflict": 2,
    "last_price_change": "há 2 dias",
    "tracked_since": "12/02/2026",
    "reputation": 3.9,
    "avg_price_diff": -1.20,
    "aggressiveness": "Alta",
    "price_changes_per_week": 8
  },
  {
    "id": "udon-distribuidora",
    "slug": "udon-distribuidora",
    "name": "Udon Distribuidora",
    "marketplaces": ["ML", "Shopee"],
    "skus_in_conflict": 5,
    "last_price_change": "há 4h",
    "tracked_since": "22/03/2026",
    "reputation": 4.3,
    "avg_price_diff": -0.45,
    "aggressiveness": "Média",
    "price_changes_per_week": 5
  },
  {
    "id": "sakura-market-online",
    "slug": "sakura-market-online",
    "name": "Sakura Market Online",
    "marketplaces": ["Amazon"],
    "skus_in_conflict": 3,
    "last_price_change": "há 12h",
    "tracked_since": "08/03/2026",
    "reputation": 4.6,
    "avg_price_diff": 0.10,
    "aggressiveness": "Baixa",
    "price_changes_per_week": 2
  },
  {
    "id": "pak-choi-store",
    "slug": "pak-choi-store",
    "name": "Pak Choi Store",
    "marketplaces": ["ML", "Shopee"],
    "skus_in_conflict": 4,
    "last_price_change": "há 30min",
    "tracked_since": "25/03/2026",
    "reputation": 4.0,
    "avg_price_diff": -0.90,
    "aggressiveness": "Alta",
    "price_changes_per_week": 10
  }
]
